loopsapi
