Metadata-Version: 2.1
Name: loopsapi
Version: 0.2
Summary: Python wrapper for the Loops.so API
Home-page: https://github.com/abrihter/loopsapi
Download-URL: https://github.com/abrihter/loopsapi/archive/refs/tags/v0.2.tar.gz
Author: abrihter
Author-email: 
License: MIT
Keywords: LOOPS,LOOPS.SO,API,WRAPPER
Classifier: Development Status :: 5 - Production/Stable
Classifier: Intended Audience :: Developers
Classifier: Topic :: Software Development :: Build Tools
Classifier: License :: OSI Approved :: MIT License
Classifier: Programming Language :: Python :: 3
License-File: LICENSE
Requires-Dist: requests
